quadprog.cp310-win_amd64.pyd
quadprog-0.1.12.dist-info/LICENSE
quadprog-0.1.12.dist-info/METADATA
quadprog-0.1.12.dist-info/WHEEL
quadprog-0.1.12.dist-info/top_level.txt
quadprog-0.1.12.dist-info/RECORD
